[
  {
    "Select":"Algeria"
  },
  {
    "Select":"Bahrain"
  },
  {
    "Select":"Egypt"
  },
  {
    "Select":"Iran"
  },
  {
    "Select":"Iraq"
  },
  {
    "Select":"Jordan"
  },
  {
    "Select":"Kuwait"
  },
  {
    "Select":"Lebanon"
  },
  {
    "Select":"Libya"
  },
  {
    "Select":"Morocco"
  },
  {
    "Select":"Oman"
  },
  {
    "Select":"Pakistan"
  },
  {
    "Select":"Qatar"
  },
  {
    "Select":"Saudi"
  },
  {
    "Select":"Somalia"
  },
  {
    "Select":"Syria"
  },
  {
    "Select":"Tunisia"
  },
  {
    "Select":"Turkey"
  },
  {
    "Select":"United"
  },
  {
    "Select":"Yemen"
  },
  {
    "Select":"Albania"
  },
  {
    "Select":"Andorra"
  },
  {
    "Select":"Armenia"
  },
  {
    "Select":"Austria"
  },
  {
    "Select":"Belarus"
  },
  {
    "Select":"Belgium"
  },
  {
    "Select":"Bosnia"
  },
  {
    "Select":"Bulgaria"
  },
  {
    "Select":"Croatia"
  },
  {
    "Select":"Cyprus"
  },
  {
    "Select":"Czech"
  },
  {
    "Select":"Denmark"
  },
  {
    "Select":"Estonia"
  },
  {
    "Select":"Finland"
  },
  {
    "Select":"France"
  },
  {
    "Select":"Georgia"
  },
  {
    "Select":"Germany"
  },
  {
    "Select":"Greece"
  },
  {
    "Select":"Hungary"
  },
  {
    "Select":"Iceland"
  },
  {
    "Select":"Ireland"
  },
  {
    "Select":"Italy"
  },
  {
    "Select":"Kosovo"
  },
  {
    "Select":"Latvia"
  },
  {
    "Select":"Liechtenstein"
  },
  {
    "Select":"Lithuania"
  },
  {
    "Select":"Luxembourg"
  },
  {
    "Select":"Macedonia"
  },
  {
    "Select":"Malta"
  },
  {
    "Select":"Moldova"
  },
  {
    "Select":"Monaco"
  },
  {
    "Select":"Montenegro"
  },
  {
    "Select":"Netherlands"
  },
  {
    "Select":"Norway"
  },
  {
    "Select":"Poland"
  },
  {
    "Select":"Portugal"
  },
  {
    "Select":"Romania"
  },
  {
    "Select":"Russia"
  },
  {
    "Select":"San"
  },
  {
    "Select":"Serbia"
  },
  {
    "Select":"Slovakia"
  },
  {
    "Select":"Slovenia"
  },
  {
    "Select":"Spain"
  },
  {
    "Select":"Sweden"
  },
  {
    "Select":"Switzerland"
  },
  {
    "Select":"Ukraine"
  },
  {
    "Select":"Canada"
  },
  {
    "Select":"Mexico"
  },
  {
    "Select":"United"
  },
  {
    "Select":"Argentina"
  },
  {
    "Select":"Bolivia"
  },
  {
    "Select":"Brazil"
  },
  {
    "Select":"Chile"
  },
  {
    "Select":"Colombia"
  },
  {
    "Select":"Ecuador"
  },
  {
    "Select":"Guyana"
  },
  {
    "Select":"Paraguay"
  },
  {
    "Select":"Peru"
  },
  {
    "Select":"Suriname"
  },
  {
    "Select":"Uruguay"
  },
  {
    "Select":"Venezuela"
  }
]